<?xml version="1.0" encoding="UTF-8"?><record_update sys_domain="global" table="sys_ux_addon_event_mapping">
    <sys_ux_addon_event_mapping action="DELETE">
        <active>true</active>
        <controller/>
        <description/>
        <name>Popular articles event mapping</name>
        <parent_macroponent display_value="Landing Page">7e1e291aa66fc2101af27da5d89f620a</parent_macroponent>
        <source_component/>
        <source_da display_value="navigation">d46f400473211010c342d5fdbdf6a7cf</source_da>
        <source_element_id>data_row_3</source_element_id>
        <sys_class_name>sys_ux_addon_event_mapping</sys_class_name>
        <sys_created_by>admin</sys_created_by>
        <sys_created_on>2024-07-25 05:04:30</sys_created_on>
        <sys_domain>global</sys_domain>
        <sys_domain_path>/</sys_domain_path>
        <sys_id>fa1e291aff6fc21024d810146be33209</sys_id>
        <sys_mod_count>0</sys_mod_count>
        <sys_name>Popular articles event mapping</sys_name>
        <sys_overrides/>
        <sys_package display_value="Employee Suite" source="x_1210077_employ_0">d7add99847230210e560de94116d436a</sys_package>
        <sys_policy/>
        <sys_scope display_value="Employee Suite">d7add99847230210e560de94116d436a</sys_scope>
        <sys_update_name>sys_ux_addon_event_mapping_fa1e291aff6fc21024d810146be33209</sys_update_name>
        <sys_updated_by>admin</sys_updated_by>
        <sys_updated_on>2024-07-25 05:04:30</sys_updated_on>
        <target_event display_value="">721e291a226fc21003050aae5d1a610a</target_event>
        <target_payload_mapping>{
    "container": {
        "sysId": {
            "binding": {
                "address": [
                    "sysId"
                ]
            },
            "type": "EVENT_PAYLOAD_BINDING"
        },
        "table": {
            "binding": {
                "address": [
                    "table"
                ]
            },
            "type": "EVENT_PAYLOAD_BINDING"
        }
    },
    "type": "MAP_CONTAINER"
}</target_payload_mapping>
    </sys_ux_addon_event_mapping>
    <sys_update_version action="INSERT_OR_UPDATE">
        <action>DELETE</action>
        <application display_value="Employee Suite">d7add99847230210e560de94116d436a</application>
        <file_path/>
        <instance_id>6d8f8c1adb9639502f082a5913961961</instance_id>
        <instance_name>dev205975</instance_name>
        <name>sys_ux_addon_event_mapping_fa1e291aff6fc21024d810146be33209</name>
        <payload><![CDATA[<?xml version="1.0" encoding="UTF-8"?><record_update sys_domain="global" table="sys_ux_addon_event_mapping"><sys_ux_addon_event_mapping action="INSERT_OR_UPDATE"><active>true</active><controller/><description/><name>Popular articles event mapping</name><parent_macroponent display_value="Landing Page">7e1e291aa66fc2101af27da5d89f620a</parent_macroponent><source_component/><source_da display_value="navigation">d46f400473211010c342d5fdbdf6a7cf</source_da><source_element_id>data_row_3</source_element_id><sys_class_name>sys_ux_addon_event_mapping</sys_class_name><sys_created_by>admin</sys_created_by><sys_created_on>2024-07-25 05:04:30</sys_created_on><sys_domain>global</sys_domain><sys_domain_path>/</sys_domain_path><sys_id>fa1e291aff6fc21024d810146be33209</sys_id><sys_mod_count>0</sys_mod_count><sys_name>Popular articles event mapping</sys_name><sys_overrides/><sys_package display_value="Employee Suite" source="x_1210077_employ_0">d7add99847230210e560de94116d436a</sys_package><sys_policy/><sys_scope display_value="Employee Suite">d7add99847230210e560de94116d436a</sys_scope><sys_update_name>sys_ux_addon_event_mapping_fa1e291aff6fc21024d810146be33209</sys_update_name><sys_updated_by>admin</sys_updated_by><sys_updated_on>2024-07-25 05:04:30</sys_updated_on><target_event display_value="">721e291a226fc21003050aae5d1a610a</target_event><target_payload_mapping>{
    "container": {
        "sysId": {
            "binding": {
                "address": [
                    "sysId"
                ]
            },
            "type": "EVENT_PAYLOAD_BINDING"
        },
        "table": {
            "binding": {
                "address": [
                    "table"
                ]
            },
            "type": "EVENT_PAYLOAD_BINDING"
        }
    },
    "type": "MAP_CONTAINER"
}</target_payload_mapping></sys_ux_addon_event_mapping></record_update>]]></payload>
        <payload_hash>1867065314</payload_hash>
        <record_name>Popular articles event mapping</record_name>
        <reverted_from/>
        <source>aba8252e836b4610b3cacb65eeaad356</source>
        <source_table>sys_update_set</source_table>
        <state>current</state>
        <sys_created_by>admin</sys_created_by>
        <sys_created_on>2024-07-25 06:09:36</sys_created_on>
        <sys_id>eba8252e836b4610b3cacb65eeaad3cc</sys_id>
        <sys_mod_count>0</sys_mod_count>
        <sys_recorded_at>190e88260a30000001</sys_recorded_at>
        <sys_updated_by>admin</sys_updated_by>
        <sys_updated_on>2024-07-25 06:09:36</sys_updated_on>
        <type>UX Add-on Event Mapping</type>
        <update_guid>f9c9d12add2b4610210402f4e3a9f218</update_guid>
        <update_guid_history>f9c9d12add2b4610210402f4e3a9f218:1867065314,0a4869ea076b4610dab08d6932dbc4e3:0,f9c9d12add2b4610210402f4e3a9f218:1867065314,e5c9912aa72b46100ffbe9b8d99a36e3:-1824928654,65763d96f9e70610c5fe6b0dd8ae0440:1351137238</update_guid_history>
    </sys_update_version>
    <sys_metadata_delete action="INSERT_OR_UPDATE">
        <sys_audit_delete/>
        <sys_class_name>sys_metadata_delete</sys_class_name>
        <sys_created_by>admin</sys_created_by>
        <sys_created_on>2024-07-25 06:09:37</sys_created_on>
        <sys_db_object display_value="" name="sys_ux_addon_event_mapping">sys_ux_addon_event_mapping</sys_db_object>
        <sys_id>00e672f2072d4e9695245bf23727b0f9</sys_id>
        <sys_metadata>fa1e291aff6fc21024d810146be33209</sys_metadata>
        <sys_mod_count>0</sys_mod_count>
        <sys_name>Popular articles event mapping</sys_name>
        <sys_package display_value="Employee Suite" source="x_1210077_employ_0">d7add99847230210e560de94116d436a</sys_package>
        <sys_parent/>
        <sys_policy/>
        <sys_scope display_value="Employee Suite">d7add99847230210e560de94116d436a</sys_scope>
        <sys_scope_delete display_value="">5344ae81d7774101bde71758731e27a9</sys_scope_delete>
        <sys_update_name>sys_ux_addon_event_mapping_fa1e291aff6fc21024d810146be33209</sys_update_name>
        <sys_update_version display_value="sys_ux_addon_event_mapping_fa1e291aff6fc21024d810146be33209">eba8252e836b4610b3cacb65eeaad3cc</sys_update_version>
        <sys_updated_by>admin</sys_updated_by>
        <sys_updated_on>2024-07-25 06:09:37</sys_updated_on>
    </sys_metadata_delete>
</record_update>
